vastion/__init__.py
vastion-0.0.1.dist-info/METADATA
vastion-0.0.1.dist-info/WHEEL
vastion-0.0.1.dist-info/top_level.txt
vastion-0.0.1.dist-info/RECORD
